azarrot/__init__.py
azarrot/__main__.py
azarrot/common_data.py
azarrot/config.py
azarrot/server.py
azarrot/backends/__init__.py
azarrot/backends/backend_base.py
azarrot/backends/common.py
azarrot/backends/ipex_llm_backend.py
azarrot/backends/openvino_backend.py
azarrot/backends/ipex_llm_support/__init__.py
azarrot/backends/ipex_llm_support/internvl2_processor.py
azarrot/backends/ipex_llm_support/internvl2_tools.py
azarrot/frontends/__init__.py
azarrot/frontends/backend_pipe.py
azarrot/frontends/management.py
azarrot/frontends/openai_frontend.py
azarrot/frontends/openai_support/__init__.py
azarrot/frontends/openai_support/openai_data.py
azarrot/models/__init__.py
azarrot/models/chat_templates.py
azarrot/models/model_manager.py
azarrot/models/model_quirks.py
azarrot/models/supports/__init__.py
azarrot/models/supports/qwen2_chat_support.py
azarrot/tools/__init__.py
azarrot/tools/tool.py
azarrot/tools/tool_adder.py
azarrot/tools/tool_manager.py
azarrot-0.2.0.dist-info/LICENSE
azarrot-0.2.0.dist-info/METADATA
azarrot-0.2.0.dist-info/WHEEL
azarrot-0.2.0.dist-info/entry_points.txt
azarrot-0.2.0.dist-info/top_level.txt
azarrot-0.2.0.dist-info/RECORD
