Metadata-Version: 2.1
Name: azarrot
Version: 0.2.0
Summary: An OpenAI compatible server, focusing on OpenVINO and IPEX-LLM usage.
Author-email: notsyncing <song.fc@gmail.com>
License: 
Classifier: Development Status :: 2 - Pre-Alpha
Classifier: Intended Audience :: End Users/Desktop
Classifier: Topic :: Internet
Classifier: License :: OSI Approved :: Apache Software License
Classifier: Programming Language :: Python :: 3.11
Requires-Python: <=3.11.99
License-File: LICENSE
Requires-Dist: openvino ==2024.3
Requires-Dist: optimum[openvino] ==1.18.1
Requires-Dist: ipex-llm[xpu] ==2.1.0b2
Requires-Dist: fastapi ==0.111.0
Requires-Dist: pyyaml ==6.0.1
Requires-Dist: decord ==0.6.0
Requires-Dist: jinja2 ==3.1.4
Provides-Extra: build
Requires-Dist: build[virtualenv] ==1.0.3 ; extra == 'build'
Provides-Extra: dev
Requires-Dist: tox ; extra == 'dev'
Requires-Dist: azarrot[lint] ; extra == 'dev'
Requires-Dist: azarrot[test] ; extra == 'dev'
Requires-Dist: azarrot[doc] ; extra == 'dev'
Requires-Dist: azarrot[build] ; extra == 'dev'
Provides-Extra: doc
Requires-Dist: sphinx ; extra == 'doc'
Provides-Extra: lint
Requires-Dist: mypy ; extra == 'lint'
Requires-Dist: ruff ; extra == 'lint'
Provides-Extra: test
Requires-Dist: pytest ==7.4.1 ; extra == 'test'
Requires-Dist: pytest-cov ==4.1.0 ; extra == 'test'
Requires-Dist: coverage[toml] ==7.3.1 ; extra == 'test'
